rabbitmqbaselibrary/__init__.py
rabbitmqbaselibrary/__version__.py
rabbitmqbaselibrary/bindings/__init__.py
rabbitmqbaselibrary/bindings/bindings.py
rabbitmqbaselibrary/common/__init__.py
rabbitmqbaselibrary/common/config.py
rabbitmqbaselibrary/common/environments.py
rabbitmqbaselibrary/common/exceptions.py
rabbitmqbaselibrary/common/handlers.py
rabbitmqbaselibrary/common/report.py
rabbitmqbaselibrary/common/templates.py
rabbitmqbaselibrary/definitions/__init__.py
rabbitmqbaselibrary/definitions/definitions.py
rabbitmqbaselibrary/exchanges/__init__.py
rabbitmqbaselibrary/exchanges/exchanges.py
rabbitmqbaselibrary/history/__init__.py
rabbitmqbaselibrary/history/history.py
rabbitmqbaselibrary/messages/__init__.py
rabbitmqbaselibrary/messages/messages.py
rabbitmqbaselibrary/policies/__init__.py
rabbitmqbaselibrary/policies/policies.py
rabbitmqbaselibrary/queues/__init__.py
rabbitmqbaselibrary/queues/queues.py
rabbitmqbaselibrary/users/__init__.py
rabbitmqbaselibrary/users/users.py
rabbitmqbaselibrary/vhost/__init__.py
rabbitmqbaselibrary/vhost/vhost.py
rabbitmq_base_library-0.8.10.dist-info/LICENSE
rabbitmq_base_library-0.8.10.dist-info/METADATA
rabbitmq_base_library-0.8.10.dist-info/WHEEL
rabbitmq_base_library-0.8.10.dist-info/top_level.txt
rabbitmq_base_library-0.8.10.dist-info/RECORD
