Metadata-Version: 2.1
Name: rabbitmq-base-library
Version: 0.8.10
Summary: rabbitmq-base-library dist
Home-page: https://github.com/davengeo/rabbitme-base-library
Author: David Navarro Alvarez
Author-email: me@davengeo.com
License: UNKNOWN
Platform: UNKNOWN
Requires-Dist: requests
Requires-Dist: argparse
Requires-Dist: pyramda
Requires-Dist: rabbitpy
